ayah_sender/__init__.py
ayah_sender/main.py
ayah_sender/reciter.py
ayah_sender/reciters.csv
ayah_sender-0.1.6.dist-info/LICENSE
ayah_sender-0.1.6.dist-info/METADATA
ayah_sender-0.1.6.dist-info/WHEEL
ayah_sender-0.1.6.dist-info/top_level.txt
ayah_sender-0.1.6.dist-info/RECORD
