Metadata-Version: 2.1
Name: ayah_sender
Version: 0.1.6
Summary: Get Quranic audio and images easily.
Home-page: https://github.com/codewithasib/ayah-sender
Author: Asib Hossen
Author-email: dev.asib@proton.me
Classifier: Programming Language :: Python :: 3
Classifier: License :: OSI Approved :: MIT License
Classifier: Operating System :: OS Independent
Requires-Python: >=3.8
License-File: LICENSE
Requires-Dist: requests
Requires-Dist: pydub
